arcana/xnat/__init__.py
arcana/xnat/_version.py
arcana/xnat/cli/__init__.py
arcana/xnat/cli/base.py
arcana/xnat/cli/entrypoint.py
arcana/xnat/cli/update_release.py
arcana/xnat/cli/tests/test_cli_add_columns.py
arcana/xnat/cli/tests/test_cli_dataset_export.py
arcana/xnat/cli/tests/test_cli_store.py
arcana/xnat/cli/tests/test_cli_xnat_images.py
arcana/xnat/data/__init__.py
arcana/xnat/data/api.py
arcana/xnat/data/cs.py
arcana/xnat/data/tests/test_store.py
arcana/xnat/deploy/__init__.py
arcana/xnat/deploy/command.py
arcana/xnat/deploy/image.py
arcana/xnat/deploy/tests/test_app.py
arcana/xnat/utils/__init__.py
arcana/xnat/utils/testing.py
arcana_xnat-0.4.1.dist-info/METADATA
arcana_xnat-0.4.1.dist-info/WHEEL
arcana_xnat-0.4.1.dist-info/licenses/LICENSE
arcana_xnat-0.4.1.dist-info/RECORD
